isa_common/__init__.py
isa_common/async_base_client.py
isa_common/async_duckdb_client.py
isa_common/async_minio_client.py
isa_common/async_mqtt_client.py
isa_common/async_nats_client.py
isa_common/async_neo4j_client.py
isa_common/async_postgres_client.py
isa_common/async_qdrant_client.py
isa_common/async_redis_client.py
isa_common/base_client.py
isa_common/consul_client.py
isa_common/duckdb_client.py
isa_common/loki_client.py
isa_common/minio_client.py
isa_common/mqtt_client.py
isa_common/nats_client.py
isa_common/neo4j_client.py
isa_common/postgres_client.py
isa_common/qdrant_client.py
isa_common/redis_client.py
isa_common/events/__init__.py
isa_common/events/base_event_models.py
isa_common/events/base_event_publisher.py
isa_common/events/base_event_subscriber.py
isa_common/events/billing_event_publisher.py
isa_common/events/billing_events.py
isa_common/proto/__init__.py
isa_common/proto/common_pb2.py
isa_common/proto/common_pb2_grpc.py
isa_common/proto/duckdb_service_pb2.py
isa_common/proto/duckdb_service_pb2_grpc.py
isa_common/proto/loki_service_pb2.py
isa_common/proto/loki_service_pb2_grpc.py
isa_common/proto/minio_service_pb2.py
isa_common/proto/minio_service_pb2_grpc.py
isa_common/proto/mqtt_service_pb2.py
isa_common/proto/mqtt_service_pb2_grpc.py
isa_common/proto/nats_service_pb2.py
isa_common/proto/nats_service_pb2_grpc.py
isa_common/proto/neo4j_service_pb2.py
isa_common/proto/neo4j_service_pb2_grpc.py
isa_common/proto/postgres_service_pb2.py
isa_common/proto/postgres_service_pb2_grpc.py
isa_common/proto/qdrant_service_pb2.py
isa_common/proto/qdrant_service_pb2_grpc.py
isa_common/proto/redis_service_pb2.py
isa_common/proto/redis_service_pb2_grpc.py
isa_common-0.2.2.dist-info/METADATA
isa_common-0.2.2.dist-info/WHEEL
isa_common-0.2.2.dist-info/top_level.txt
isa_common-0.2.2.dist-info/RECORD
