Metadata-Version: 2.4
Name: isa-common
Version: 0.2.2
Summary: Shared Python infrastructure library for isA platform
Home-page: https://github.com/isa-platform/isA_Cloud
Author: isA Platform
Author-email: isA Platform <dev@isa-platform.com>
Project-URL: Homepage, https://github.com/isa-platform/isA_Cloud
Project-URL: Repository, https://github.com/isa-platform/isA_Cloud
Classifier: Development Status :: 3 - Alpha
Classifier: Intended Audience :: Developers
Classifier: Programming Language :: Python :: 3
Classifier: Programming Language :: Python :: 3.8
Classifier: Programming Language :: Python :: 3.9
Classifier: Programming Language :: Python :: 3.10
Classifier: Programming Language :: Python :: 3.11
Requires-Python: >=3.8
Requires-Dist: grpcio>=1.50.0
Requires-Dist: grpcio-tools>=1.50.0
Requires-Dist: pydantic>=2.0.0
Requires-Dist: tenacity>=8.0.0
Requires-Dist: python-consul2>=0.1.5
Requires-Dist: asyncpg>=0.29.0
Provides-Extra: dev
Requires-Dist: pytest>=7.0.0; extra == "dev"
Requires-Dist: pytest-asyncio>=0.21.0; extra == "dev"
Requires-Dist: black>=23.0.0; extra == "dev"
Requires-Dist: flake8>=6.0.0; extra == "dev"
Requires-Dist: mypy>=1.0.0; extra == "dev"
Dynamic: author
Dynamic: home-page
Dynamic: requires-python
